pdiffcopy/__init__.py
pdiffcopy/__main__.py
pdiffcopy/cli.py
pdiffcopy/client.py
pdiffcopy/exceptions.py
pdiffcopy/hashing.py
pdiffcopy/mp.py
pdiffcopy/operations.py
pdiffcopy/server.py
pdiffcopy/tests.py
pdiffcopy-1.0.1.dist-info/LICENSE.txt
pdiffcopy-1.0.1.dist-info/METADATA
pdiffcopy-1.0.1.dist-info/WHEEL
pdiffcopy-1.0.1.dist-info/entry_points.txt
pdiffcopy-1.0.1.dist-info/top_level.txt
pdiffcopy-1.0.1.dist-info/RECORD
